ChuanzhiboKeCuixifanJavaWebJiangyiDay0117/README.md
ChuanzhiboKeCuixifanJavaWebJiangyiDay0117/__init__.py
ChuanzhiboKeCuixifanJavaWebJiangyiDay0117/__main__.py
ChuanzhiboKeCuixifanJavaWebJiangyiDay0117/file.pdf
ChuanzhiboKeCuixifanJavaWebJiangyiDay0117/index.html
chuanzhibo_ke_cuixifan_java_web_jiangyi_day01_17-2024.3.5.0.dist-info/METADATA
chuanzhibo_ke_cuixifan_java_web_jiangyi_day01_17-2024.3.5.0.dist-info/WHEEL
chuanzhibo_ke_cuixifan_java_web_jiangyi_day01_17-2024.3.5.0.dist-info/entry_points.txt
chuanzhibo_ke_cuixifan_java_web_jiangyi_day01_17-2024.3.5.0.dist-info/top_level.txt
chuanzhibo_ke_cuixifan_java_web_jiangyi_day01_17-2024.3.5.0.dist-info/RECORD
